promis/__init__.py
promis/coco.py
promis/promis.py
promis/star_map.py
promis/estimators/__init__.py
promis/estimators/filters/__init__.py
promis/estimators/filters/extended_gmphd.py
promis/estimators/filters/extended_kalman.py
promis/estimators/filters/gmphd.py
promis/estimators/filters/kalman.py
promis/estimators/filters/unscented_kalman.py
promis/estimators/smoothers/__init__.py
promis/estimators/smoothers/extended_rts.py
promis/estimators/smoothers/rts.py
promis/estimators/smoothers/unscented_rts.py
promis/geo/__init__.py
promis/geo/collection.py
promis/geo/geospatial.py
promis/geo/helpers.py
promis/geo/location.py
promis/geo/map.py
promis/geo/polygon.py
promis/geo/polyline.py
promis/geo/raster_band.py
promis/gui/__init__.py
promis/gui/cli.py
promis/gui/main.py
promis/gui/data/default_layer.json
promis/gui/data/default_loc_table.json
promis/gui/frontend/asset-manifest.json
promis/gui/frontend/favicon.ico
promis/gui/frontend/index.html
promis/gui/frontend/logo.png
promis/gui/frontend/logo192.png
promis/gui/frontend/logo512.png
promis/gui/frontend/manifest.json
promis/gui/frontend/robots.txt
promis/gui/frontend/static/css/main.85522a89.css
promis/gui/frontend/static/css/main.85522a89.css.map
promis/gui/frontend/static/js/453.5b6c0a6a.chunk.js
promis/gui/frontend/static/js/453.5b6c0a6a.chunk.js.map
promis/gui/frontend/static/js/main.2a48a5fe.js
promis/gui/frontend/static/js/main.2a48a5fe.js.LICENSE.txt
promis/gui/frontend/static/js/main.2a48a5fe.js.map
promis/gui/frontend/static/media/drone_new.f5cfefaf8086d8705950.svg
promis/gui/frontend/static/media/landing-pad-marker.e229022f3075737f4292.png
promis/gui/models/__init__.py
promis/gui/models/colors.py
promis/gui/models/config.py
promis/gui/models/connection_manager.py
promis/gui/models/layer.py
promis/gui/models/line.py
promis/gui/models/location_type_table.py
promis/gui/models/marker.py
promis/gui/models/polygon.py
promis/gui/models/run_request.py
promis/loaders/__init__.py
promis/loaders/nautical_loader.py
promis-2.0.0.dist-info/licenses/LICENSE.md
promis-2.0.0.dist-info/METADATA
promis-2.0.0.dist-info/WHEEL
promis-2.0.0.dist-info/entry_points.txt
promis-2.0.0.dist-info/top_level.txt
promis-2.0.0.dist-info/RECORD
