Metadata-Version: 2.4
Name: promis
Version: 2.0.0
Summary: A Python package to apply probabilistic logic programming to navigation tasks.
Home-page: 
Author: Simon Kohaut
Author-email: simon.kohaut@cs.tu-darmstadt.de
Classifier: Programming Language :: Python :: 3
Classifier: License :: OSI Approved :: BSD License
Classifier: Operating System :: OS Independent
Requires-Python: >=3.10
License-File: LICENSE.md
Requires-Dist: rich
Requires-Dist: tqdm
Requires-Dist: numpy
Requires-Dist: scipy
Requires-Dist: scikit-learn
Requires-Dist: pandas
Requires-Dist: matplotlib
Requires-Dist: pyproj
Requires-Dist: geojson
Requires-Dist: geopy
Requires-Dist: shapely
Requires-Dist: overpy
Requires-Dist: geojson_pydantic
Requires-Dist: nflows
Requires-Dist: torch
Requires-Dist: pyro-ppl
Requires-Dist: pysdd
Requires-Dist: gpytorch
Requires-Dist: fastapi[standard]
Requires-Dist: graphviz
Requires-Dist: seaborn
Requires-Dist: smopy
Requires-Dist: ipywidgets
Requires-Dist: requests
Provides-Extra: doc
Requires-Dist: sphinx; extra == "doc"
Requires-Dist: nbsphinx; extra == "doc"
Requires-Dist: sphinx-markdown-builder; extra == "doc"
Requires-Dist: sphinx_rtd_theme; extra == "doc"
Requires-Dist: sphinxcontrib-programoutput; extra == "doc"
Provides-Extra: nautical
Requires-Dist: gdal; extra == "nautical"
Provides-Extra: dev
Requires-Dist: black; extra == "dev"
Requires-Dist: ruff; extra == "dev"
Requires-Dist: pytest; extra == "dev"
Dynamic: author
Dynamic: author-email
Dynamic: classifier
Dynamic: description
Dynamic: description-content-type
Dynamic: license-file
Dynamic: provides-extra
Dynamic: requires-dist
Dynamic: requires-python
Dynamic: summary
